aldryn_client/__init__.py
aldryn_client/api_requests.py
aldryn_client/check_system.py
aldryn_client/cli.py
aldryn_client/cloud.py
aldryn_client/config.py
aldryn_client/exceptions.py
aldryn_client/forms.py
aldryn_client/messages.py
aldryn_client/settings.py
aldryn_client/utils.py
aldryn_client/localdev/__init__.py
aldryn_client/localdev/main.py
aldryn_client/localdev/utils.py
aldryn_client/upload/__init__.py
aldryn_client/upload/addon.py
aldryn_client/upload/boilerplate.py
aldryn_client/upload/common.py
aldryn_client/validators/__init__.py
aldryn_client/validators/addon.py
aldryn_client/validators/boilerplate.py
aldryn_client/validators/common.py
aldryn_client-2.3.5.dist-info/DESCRIPTION.rst
aldryn_client-2.3.5.dist-info/entry_points.txt
aldryn_client-2.3.5.dist-info/METADATA
aldryn_client-2.3.5.dist-info/metadata.json
aldryn_client-2.3.5.dist-info/RECORD
aldryn_client-2.3.5.dist-info/top_level.txt
aldryn_client-2.3.5.dist-info/WHEEL
