Metadata-Version: 2.0
Name: aldryn-client
Version: 2.3.5
Summary: The command-line client for the Aldryn Cloud
Home-page: http://www.aldryn.com/
Author: Divio AG
Author-email: aldryn@divio.ch
License: BSD
Platform: OS Independent
Requires-Dist: click
Requires-Dist: requests
Requires-Dist: tabulate
Requires-Dist: six
